bin/__init__.py
bin/cleanup.sh
bin/create-egg.sh
bin/install_locally.py
bin/mcenter_components_setup.py
bin/mlpiper
bin/show_requirements.py
mlpiper/__init__.py
mlpiper/main.py
mlpiper/cli/__init__.py
mlpiper/cli/main.py
mlpiper/cli/mlpiper_exception.py
mlpiper/cli/mlpiper_runner.py
mlpiper/cli/wizard_flow.py
mlpiper/cli/wizard_modules.py
mlpiper/cli/wizard_shell.py
mlpiper/cli/deps_install/__init__.py
mlpiper/cli/deps_install/package_installer.py
mlpiper/cli/deps_install/py_package_installer.py
mlpiper/cli/deps_install/r_package_installer.py
mlpiper/common/__init__.py
mlpiper/common/attr_dict.py
mlpiper/common/base.py
mlpiper/common/bg_actor.py
mlpiper/common/buff_to_lines.py
mlpiper/common/byte_conv.py
mlpiper/common/cached_property.py
mlpiper/common/constants.py
mlpiper/common/external_model_info.py
mlpiper/common/mlpiper_exception.py
mlpiper/common/model_connector_constants.py
mlpiper/common/model_connector_helper.py
mlpiper/common/os_util.py
mlpiper/common/process_monitor.py
mlpiper/common/singleton.py
mlpiper/common/topological_sort.py
mlpiper/common/verbose_printer.py
mlpiper/components/__init__.py
mlpiper/components/command_line_parser.py
mlpiper/components/component.py
mlpiper/components/connectable_component.py
mlpiper/components/connectable_external_component.py
mlpiper/components/connected_component_info.py
mlpiper/components/external_component.py
mlpiper/components/parameter.py
mlpiper/components/restful_component.py
mlpiper/components/spark_context_component.py
mlpiper/components/spark_data_component.py
mlpiper/components/spark_pipeline_model_helper.py
mlpiper/components/spark_session_component.py
mlpiper/components/spark_stage_component.py
mlpiper/components/restful/__init__.py
mlpiper/components/restful/__template__.py
mlpiper/components/restful/constants.py
mlpiper/components/restful/flask_app_wrapper.py
mlpiper/components/restful/flask_custom_json_encoder.py
mlpiper/components/restful/flask_route.py
mlpiper/components/restful/metric.py
mlpiper-2.6.2.dist-info/METADATA
mlpiper-2.6.2.dist-info/WHEEL
mlpiper-2.6.2.dist-info/entry_points.txt
mlpiper-2.6.2.dist-info/top_level.txt
mlpiper-2.6.2.dist-info/RECORD
