Metadata-Version: 2.1
Name: mlpiper
Version: 2.6.2
Summary: An engine for running component based ML pipelines
Home-page: https://github.com/datarobot/mlpiper
Author: DataRobot
Author-email: info@datarobot.com
License: Apache License 2.0
Classifier: Programming Language :: Python :: 2
Classifier: Programming Language :: Python :: 3
Classifier: License :: OSI Approved :: Apache Software License
Classifier: Operating System :: MacOS
Classifier: Operating System :: POSIX
Classifier: Operating System :: Unix
Requires-Python: >=2.7, !=3.0.*, !=3.1.*, !=3.2.*, !=3.3.*
Requires-Dist: termcolor
Requires-Dist: flask
Requires-Dist: flask-cors
Requires-Dist: psutil
Requires-Dist: future
Requires-Dist: py4j ~=0.10.9.0
Provides-Extra: pyspark
Requires-Dist: pyspark ; extra == 'pyspark'
Provides-Extra: sagemaker
Requires-Dist: sagemaker ; extra == 'sagemaker'
Requires-Dist: pytz ; extra == 'sagemaker'
Requires-Dist: numpy ==1.14.6 ; (python_version < "3.4") and extra == 'sagemaker'
Requires-Dist: scipy ==1.1.0 ; (python_version < "3.4") and extra == 'sagemaker'
Provides-Extra: uwsgi
Requires-Dist: uwsgi ; extra == 'uwsgi'
Provides-Extra: wizard
Requires-Dist: pypsi ; (python_version >= "3.4") and extra == 'wizard'
